MANIFEST.in
README.rst
setup.cfg
setup.py
yxspkg_songzgif/4.jpg
yxspkg_songzgif/CutImageWidget.py
yxspkg_songzgif/__init__.py
yxspkg_songzgif/gif.py
yxspkg_songzgif/run.py
yxspkg_songzgif/sdf.png
yxspkg_songzgif.egg-info/PKG-INFO
yxspkg_songzgif.egg-info/SOURCES.txt
yxspkg_songzgif.egg-info/dependency_links.txt
yxspkg_songzgif.egg-info/requires.txt
yxspkg_songzgif.egg-info/top_level.txt
yxspkg_songzgif/__pycache__/CutImageWidget.cpython-36.pyc
yxspkg_songzgif/__pycache__/Desktop.cpython-36.pyc
yxspkg_songzgif/__pycache__/__init__.cpython-36.pyc
yxspkg_songzgif/__pycache__/gif.cpython-36.pyc
yxspkg_songzgif/__pycache__/yxspkg_songzviewer.cpython-36.pyc