Metadata-Version: 1.1
Name: yxspkg-songzgif
Version: 1.4.0
Summary: A GUI to make gif based on pyqt5
Home-page: https://github.com/blacksong
Author: Blacksong
Author-email: blacksong@qq.com
License: UNKNOWN
Platform: UNKNOWN
Classifier: Programming Language :: Python :: 3
Classifier: Operating System :: OS Independent
Classifier: Topic :: Software Development :: Libraries :: Python Modules
